odoo/addons/stay_api/README.rst
odoo/addons/stay_api/__init__.py
odoo/addons/stay_api/__manifest__.py
odoo/addons/stay_api/post_install.py
odoo/addons/stay_api/data/mail_template.xml
odoo/addons/stay_api/data/res_users.xml
odoo/addons/stay_api/i18n/fr.po
odoo/addons/stay_api/models/__init__.py
odoo/addons/stay_api/models/fastapi_endpoint.py
odoo/addons/stay_api/models/res_partner_title.py
odoo/addons/stay_api/models/stay_stay.py
odoo/addons/stay_api/models/stay_type.py
odoo/addons/stay_api/readme/CONTRIBUTORS.md
odoo/addons/stay_api/readme/DESCRIPTION.md
odoo/addons/stay_api/readme/INSTALL.md
odoo/addons/stay_api/routers/__init__.py
odoo/addons/stay_api/routers/stay.py
odoo/addons/stay_api/schemas/__init__.py
odoo/addons/stay_api/schemas/stay_create.py
odoo/addons/stay_api/schemas/stay_created.py
odoo/addons/stay_api/schemas/stay_match.py
odoo/addons/stay_api/schemas/stay_read.py
odoo/addons/stay_api/schemas/stay_update.py
odoo/addons/stay_api/security/ir.model.access.csv
odoo/addons/stay_api/static/description/icon.png
odoo/addons/stay_api/static/description/index.html
odoo/addons/stay_api/views/res_partner_title.xml
odoo/addons/stay_api/views/stay_stay.xml
odoo/addons/stay_api/views/stay_type.xml
odoo/addons/stay_api/wizards/__init__.py
odoo/addons/stay_api/wizards/res_config_settings.py
odoo/addons/stay_api/wizards/res_config_settings_view.xml
odoo/addons/stay_api/wizards/stay_create_partner.py
odoo/addons/stay_api/wizards/stay_create_partner_view.xml
odoo14_addon_stay_api-14.0.3.3.0.dist-info/METADATA
odoo14_addon_stay_api-14.0.3.3.0.dist-info/WHEEL
odoo14_addon_stay_api-14.0.3.3.0.dist-info/top_level.txt
odoo14_addon_stay_api-14.0.3.3.0.dist-info/RECORD
