Metadata-Version: 2.1
Name: odoo14-addon-stay_api
Version: 14.0.3.3.0
Summary: API for stay module
Home-page: https://github.com/OCA/vertical-abbey
Author: Akretion, Odoo Community Association (OCA)
Author-email: support@odoo-community.org
License: AGPL-3
Classifier: Programming Language :: Python
Classifier: Framework :: Odoo
Classifier: Framework :: Odoo :: 14.0
Classifier: License :: OSI Approved :: GNU Affero General Public License v3
Requires-Python: >=3.6
Requires-Dist: fastapi
Requires-Dist: odoo14-addon-fastapi
Requires-Dist: odoo14-addon-stay
Requires-Dist: odoo<14.1dev,>=14.0a
Requires-Dist: pydantic<2
